hitcpy/__init__.py
hitcpy/hitcpy.py
hitcpy/version.py
hitcpy-0.1.1.dist-info/DESCRIPTION.rst
hitcpy-0.1.1.dist-info/entry_points.txt
hitcpy-0.1.1.dist-info/METADATA
hitcpy-0.1.1.dist-info/metadata.json
hitcpy-0.1.1.dist-info/RECORD
hitcpy-0.1.1.dist-info/top_level.txt
hitcpy-0.1.1.dist-info/WHEEL
