Metadata-Version: 2.0
Name: hitcpy
Version: 0.1.1
Summary: Python client for a running HITC API
Home-page: http://github.com/nupic-community/hitc-py
Author: Jonathan Mackenzie
Author-email: jonmac1@gmail.com
License: AGPLv3
Keywords: htm,api,rest,nupic,client
Platform: UNKNOWN
Classifier: Development Status :: 5 - Production/Stable
Classifier: Environment :: Console
Classifier: Intended Audience :: Developers
Classifier: License :: OSI Approved :: GNU Affero General Public License v3 or later (AGPLv3+)
Classifier: Natural Language :: English
Classifier: Operating System :: OS Independent
Classifier: Programming Language :: Python
Requires-Dist: requests (==2.3.0)
